sft/__init__.py
sft/browser.py
sft/cli.py
sft/index.py
sft_cli-0.1.0.dist-info/METADATA
sft_cli-0.1.0.dist-info/WHEEL
sft_cli-0.1.0.dist-info/entry_points.txt
sft_cli-0.1.0.dist-info/RECORD
