Metadata-Version: 2.4
Name: sft-cli
Version: 0.1.0
Summary: An interactive terminal browser for .safetensors files
Project-URL: Homepage, https://github.com/matanby/sft-cli
Project-URL: Repository, https://github.com/matanby/sft-cli
Author: Matan Ben-Yosef
License: MIT
Keywords: browser,cli,machine-learning,safetensors,tui
Classifier: Development Status :: 3 - Alpha
Classifier: Environment :: Console
Classifier: Intended Audience :: Developers
Classifier: Intended Audience :: Science/Research
Classifier: License :: OSI Approved :: MIT License
Classifier: Programming Language :: Python :: 3
Classifier: Programming Language :: Python :: 3.9
Classifier: Programming Language :: Python :: 3.10
Classifier: Programming Language :: Python :: 3.11
Classifier: Programming Language :: Python :: 3.12
Classifier: Topic :: Scientific/Engineering :: Artificial Intelligence
Classifier: Topic :: Utilities
Requires-Python: >=3.9
Requires-Dist: textual>=0.40
Requires-Dist: typer>=0.9
